django_polyfield/__init__.py
django_polyfield/_dictable.py
django_polyfield/_fields.py
django_polyfield/_list.py
django_polyfield/_postgres_lookups.py
django_polyfield/_utils.py
django_polyfield/postgres.py
django_polyfield/serialization.py
django_polyfield-0.1.0.dist-info/DESCRIPTION.rst
django_polyfield-0.1.0.dist-info/LICENSE.txt
django_polyfield-0.1.0.dist-info/METADATA
django_polyfield-0.1.0.dist-info/RECORD
django_polyfield-0.1.0.dist-info/WHEEL
django_polyfield-0.1.0.dist-info/metadata.json
django_polyfield-0.1.0.dist-info/top_level.txt
testapp_polyfield_basic/__init__.py
testapp_polyfield_basic/animals.py
testapp_polyfield_basic/models.py
testapp_polyfield_basic/serializers.py
testapp_polyfield_basic/migrations/0001_initial.py
testapp_polyfield_basic/migrations/__init__.py
testapp_polyfield_pg/__init__.py
testapp_polyfield_pg/models.py
testapp_polyfield_pg/migrations/0001_initial.py
testapp_polyfield_pg/migrations/__init__.py
