Metadata-Version: 2.0
Name: django-polyfield
Version: 0.1.0
Summary: Django Polyfield
Home-page: https://github.com/suutari/django-polyfield
Author: Tuomas Suutari
Author-email: tuomas@nepnep.net
License: MIT
Keywords: django,polymorphic,field,json
Platform: any
Classifier: Development Status :: 2 - Pre-Alpha
Classifier: Framework :: Django
Classifier: Framework :: Django :: 1.8
Classifier: Framework :: Django :: 1.9
Classifier: Framework :: Django :: 1.10
Classifier: Framework :: Django :: 1.11
Classifier: Intended Audience :: Developers
Classifier: License :: OSI Approved :: MIT License
Classifier: Operating System :: OS Independent
Classifier: Programming Language :: Python
Classifier: Programming Language :: Python :: 2
Classifier: Programming Language :: Python :: 2.7
Classifier: Programming Language :: Python :: 3
Classifier: Programming Language :: Python :: 3.4
Classifier: Programming Language :: Python :: 3.5
Classifier: Programming Language :: Python :: 3.6
Classifier: Topic :: Software Development :: Libraries :: Python Modules
Requires-Dist: django (<2,>=1.8)
Requires-Dist: setuptools-gitver (~=1.0)
